g42cloudsdkcse/__init__.py
g42cloudsdkcse/v1/__init__.py
g42cloudsdkcse/v1/cse_async_client.py
g42cloudsdkcse/v1/cse_client.py
g42cloudsdkcse/v1/model/__init__.py
g42cloudsdkcse/v1/model/cluster_node.py
g42cloudsdkcse/v1/model/create_engine_request.py
g42cloudsdkcse/v1/model/create_engine_response.py
g42cloudsdkcse/v1/model/create_kie_req.py
g42cloudsdkcse/v1/model/delete_engine_request.py
g42cloudsdkcse/v1/model/delete_engine_response.py
g42cloudsdkcse/v1/model/doc_failed_of_upload.py
g42cloudsdkcse/v1/model/download_kie_req_body.py
g42cloudsdkcse/v1/model/download_kie_request.py
g42cloudsdkcse/v1/model/download_kie_response.py
g42cloudsdkcse/v1/model/download_kie_response_body_metadata.py
g42cloudsdkcse/v1/model/engine_create_req.py
g42cloudsdkcse/v1/model/engine_external_entrypoint.py
g42cloudsdkcse/v1/model/engine_rbac_pwd.py
g42cloudsdkcse/v1/model/engine_reference.py
g42cloudsdkcse/v1/model/engine_simple_info.py
g42cloudsdkcse/v1/model/entrypoint_item.py
g42cloudsdkcse/v1/model/flavor_brief.py
g42cloudsdkcse/v1/model/get_kie_configs.py
g42cloudsdkcse/v1/model/list_engines_request.py
g42cloudsdkcse/v1/model/list_engines_response.py
g42cloudsdkcse/v1/model/list_flavors_request.py
g42cloudsdkcse/v1/model/list_flavors_response.py
g42cloudsdkcse/v1/model/show_engine_job_request.py
g42cloudsdkcse/v1/model/show_engine_job_response.py
g42cloudsdkcse/v1/model/show_engine_request.py
g42cloudsdkcse/v1/model/show_engine_response.py
g42cloudsdkcse/v1/model/spec.py
g42cloudsdkcse/v1/model/spec_cluster_node.py
g42cloudsdkcse/v1/model/task.py
g42cloudsdkcse/v1/model/task_executor_brief.py
g42cloudsdkcse/v1/model/task_steps.py
g42cloudsdkcse/v1/model/upload_kie_request.py
g42cloudsdkcse/v1/model/upload_kie_request_body.py
g42cloudsdkcse/v1/model/upload_kie_response.py
g42cloudsdkcse/v1/region/__init__.py
g42cloudsdkcse/v1/region/cse_region.py
g42cloudsdkcse-0.0.10b0.dist-info/LICENSE
g42cloudsdkcse-0.0.10b0.dist-info/METADATA
g42cloudsdkcse-0.0.10b0.dist-info/WHEEL
g42cloudsdkcse-0.0.10b0.dist-info/top_level.txt
g42cloudsdkcse-0.0.10b0.dist-info/RECORD
